AlzPy/__init__.py
AlzPy/data_analysis.py
AlzPy/data_processing.py
AlzPy/tests/__init__.py
AlzPy/tests/test_data_analysis.py
AlzPy/tests/test_data_processing.py
AlzPy-0.1.5.dist-info/LICENSE
AlzPy-0.1.5.dist-info/METADATA
AlzPy-0.1.5.dist-info/WHEEL
AlzPy-0.1.5.dist-info/top_level.txt
AlzPy-0.1.5.dist-info/RECORD
